{
    "I": 29.959,
    "V": 14.877,
    "V7": 12.816,
    "I6": 5.203,
    "IV": 2.65,
    "I64": 2.545,
    "V65": 2.46,
    "ii6": 2.288,
    "V6": 2.074,
    "V2": 1.841,
    "vi": 1.777,
    "ii": 1.63,
    "V7/V": 1.194,
    "V43": 1.144,
    "I/V": 0.906,
    "V/V": 0.815,
    "IV64": 0.802,
    "viio": 0.718,
    "IV6": 0.629,
    "V65/V": 0.577,
    "ii65": 0.545,
    "Cad64/V": 0.497,
    "viio6": 0.451,
    "V65/ii": 0.425,
    "viio7/V": 0.409,
    "V7/IV": 0.362,
    "I6/V": 0.353,
    "V7/ii": 0.347,
    "V/ii": 0.31,
    "V6/V": 0.27,
    "viio7": 0.267,
    "i": 0.257,
    "V2/IV": 0.25,
    "I/bVI": 0.244,
    "V2/V": 0.244,
    "V/vi": 0.244,
    "iii": 0.221,
    "V43/V": 0.218,
    "viio6/V": 0.204,
    "viio7/vi": 0.201,
    "V7/vi": 0.195,
    "ii2": 0.172,
    "IV/V": 0.169,
    "viio65/V": 0.166,
    "viio/V": 0.158,
    "V65/IV": 0.144,
    "ii7": 0.144,
    "viio7/V/vi": 0.144,
    "ii/V": 0.135,
    "iv6": 0.123,
    "i/ii": 0.123,
    "vi6": 0.123,
    "V64": 0.118,
    "ii6/V": 0.118,
    "vii\u00f87/V": 0.113,
    "V2/ii": 0.109,
    "iii6": 0.098,
    "viio43": 0.095,
    "V43/ii": 0.095,
    "V9": 0.092,
    "i/vi": 0.086,
    "I/IV": 0.086,
    "-VI": 0.083,
    "V65/vi": 0.08,
    "viio/ii": 0.08,
    "i6": 0.078,
    "V/IV": 0.078,
    "V7/bIII": 0.078,
    "vii\u00f87": 0.072,
    "ii64": 0.072,
    "Cad64/II": 0.069,
    "V7/II": 0.069,
    "vi2": 0.069,
    "viio7/ii": 0.066,
    "V6/ii": 0.063,
    "iv64": 0.063,
    "i64/ii": 0.057,
    "viio65/ii": 0.057,
    "Cad64": 0.055,
    "vi7": 0.052,
    "viio43/ii": 0.052,
    "I64/bIII": 0.052,
    "viio64": 0.05,
    "V43/IV": 0.049,
    "IV/V[I]": 0.049,
    "I/bIII": 0.046,
    "V/bVI": 0.043,
    "viio2": 0.043,
    "i6/v/vi": 0.043,
    "iv": 0.04,
    "vi/V": 0.04,
    "IV6/V": 0.04,
    "IV64/V": 0.04,
    "i64": 0.04,
    "V/bIII": 0.04,
    "viio7/V/V": 0.037,
    "ii7/V": 0.037,
    "IV7": 0.037,
    "IV65": 0.034,
    "viio43/V": 0.034,
    "Ger/vi": 0.034,
    "Cad64/vi": 0.034,
    "V65/V/vi": 0.034,
    "V7/iii": 0.034,
    "V65/iii": 0.034,
    "ii\u00f843": 0.032,
    "V65/bVI": 0.032,
    "V43/vi": 0.032,
    "It/V": 0.029,
    "IV/bVI": 0.029,
    "viio64/V": 0.029,
    "V6/vi": 0.026,
    "V7/IV/V": 0.026,
    "iio6": 0.026,
    "i6/vi": 0.026,
    "I/VI/ii": 0.026,
    "viio/vi": 0.026,
    "V65/V/ii": 0.023,
    "I6/ii": 0.023,
    "V2/bVI": 0.023,
    "V7/bVI": 0.023,
    "I6/bVI": 0.023,
    "V64/V": 0.023,
    "v": 0.023,
    "I/#IV": 0.023,
    "V/#IV": 0.023,
    "V7/VII": 0.023,
    "I/VI": 0.023,
    "V6/VI": 0.023,
    "viio6/ii": 0.023,
    "V/V/V": 0.023,
    "viio65/iii": 0.023,
    "viio/IV": 0.023,
    "-III": 0.023,
    "i6/ii": 0.02,
    "i64/vi": 0.02,
    "V2/vi": 0.02,
    "viio2/vi": 0.02,
    "ii43": 0.019,
    "V7/v/vi": 0.017,
    "i/v/vi": 0.017,
    "I6/IV": 0.017,
    "V7/VI/ii": 0.017,
    "V6/IV": 0.017,
    "VI/vi": 0.017,
    "ii/V[vi]": 0.017,
    "viio/ii/V": 0.017,
    "IV/ii": 0.017,
    "iio/ii": 0.017,
    "V65/vi/V": 0.017,
    "V7/ii/V": 0.017,
    "i/iii": 0.017,
    "IV+": 0.017,
    "V65/V/V": 0.017,
    "ii/bIII[iv]": 0.017,
    "i/bIII": 0.017,
    "-VI/bIII": 0.017,
    "iv/bIII": 0.017,
    "viio7/V/II": 0.017,
    "I/II": 0.017,
    "V65/bIII": 0.017,
    "V43/bIII": 0.017,
    "iii7": 0.017,
    "iiio64": 0.017,
    "vii\u00f843": 0.014,
    "viio6/IV": 0.014,
    "I64/bVI": 0.014,
    "vi65": 0.014,
    "iv6/ii": 0.014,
    "viio43/iv/ii": 0.014,
    "V65M9": 0.014,
    "vii\u00f865/V": 0.011,
    "iio64": 0.011,
    "V43M9": 0.011,
    "I64/V": 0.011,
    "IV/bIII": 0.011,
    "I6/bIII": 0.011,
    "IV/#IV": 0.011,
    "I6/#IV": 0.011,
    "V/VI": 0.011,
    "V43/VI": 0.011,
    "I6/VI": 0.011,
    "V7M9": 0.011,
    "ii/IV": 0.011,
    "IV/IV": 0.011,
    "iii/V": 0.011,
    "V7/V/V": 0.011,
    "V6/V/V": 0.011,
    "vi64": 0.011,
    "I+": 0.011,
    "IV43": 0.011,
    "Cad64/ii": 0.011,
    "viio65/V/V": 0.011,
    "IV64/bVI": 0.011,
    "IV6/bVI": 0.011,
    "V7/ii/bVI": 0.011,
    "ii/bVI": 0.011,
    "V43/iii": 0.011,
    "bII6/bIII": 0.011,
    "-VI65": 0.011,
    "Ger65": 0.011,
    "V64/IV": 0.011
}