{
    "I": 25.061,
    "V7": 11.935,
    "I6": 7.519,
    "V": 6.883,
    "ii6": 3.881,
    "IV": 3.706,
    "I64": 2.986,
    "V43": 2.982,
    "Cad64": 2.787,
    "V65": 2.68,
    "V2": 2.346,
    "vi": 1.991,
    "V6": 1.98,
    "ii": 1.949,
    "IV6": 1.62,
    "viio6": 0.992,
    "ii65": 0.875,
    "viio": 0.72,
    "viio7/V": 0.596,
    "V7/IV": 0.586,
    "V65/V": 0.57,
    "vi6": 0.498,
    "viio6/V": 0.464,
    "i": 0.459,
    "V65/IV": 0.417,
    "ii7": 0.371,
    "IV64": 0.326,
    "V65/ii": 0.315,
    "viio43": 0.304,
    "iii6": 0.28,
    "V7/ii": 0.272,
    "V2/IV": 0.263,
    "viio7": 0.262,
    "iii": 0.222,
    "V7/V": 0.217,
    "V43/V": 0.213,
    "i6": 0.21,
    "iv6": 0.207,
    "V43/IV": 0.201,
    "viio/V": 0.2,
    "bVI": 0.198,
    "V7/vi": 0.195,
    "viio64": 0.194,
    "viio7/vi": 0.192,
    "V64": 0.19,
    "I[no5][no3][add6][add4]": 0.189,
    "Ger6": 0.184,
    "viio43/V": 0.182,
    "vi7": 0.174,
    "I[no3][add9][add4]": 0.17,
    "V43/ii": 0.166,
    "viio2": 0.166,
    "V2/V": 0.164,
    "vii\u00f87/V": 0.153,
    "V[no3][add4]": 0.152,
    "I[no3][add9][add7][add4]": 0.151,
    "Ger65": 0.151,
    "V65/vi": 0.145,
    "#viio65/ii": 0.143,
    "#viio43/ii": 0.141,
    "It6": 0.14,
    "vii\u00f87": 0.135,
    "#viio7/vi": 0.128,
    "V/ii": 0.125,
    "V7[no3][add4]": 0.125,
    "V/vi": 0.117,
    "V/V": 0.111,
    "vii\u00f865": 0.11,
    "ii2": 0.11,
    "viio65": 0.094,
    "V6/vi": 0.093,
    "V2/ii": 0.091,
    "iv": 0.088,
    "V+6/IV": 0.088,
    "vi65": 0.085,
    "V6/V": 0.081,
    "V6/ii": 0.08,
    "viio65/V": 0.079,
    "viio7/iii": 0.073,
    "vi64": 0.07,
    "#viio65/vi": 0.07,
    "viio/IV": 0.068,
    "I+": 0.067,
    "viio2/V": 0.066,
    "v6": 0.065,
    "ii\u00f87": 0.065,
    "viio43/IV": 0.061,
    "I7": 0.061,
    "#viio6/ii": 0.058,
    "viio/ii": 0.058,
    "viio7/ii": 0.056,
    "i64": 0.055,
    "I[add9][add7]": 0.052,
    "iv64": 0.052,
    "bVI6": 0.052,
    "ii\u00f843": 0.052,
    "viio65/ii": 0.052,
    "viio43/ii": 0.051,
    "v": 0.05,
    "viio6/ii": 0.05,
    "iii65": 0.049,
    "V2/iii": 0.049,
    "#viio7/ii": 0.048,
    "vi2": 0.046,
    "#viio/ii": 0.044,
    "Cad64/ii": 0.044,
    "V[no5][no3][addb6][add4]": 0.044,
    "V43/vi": 0.044,
    "iio": 0.043,
    "viio2/vi": 0.043,
    "viio2/IV": 0.043,
    "I[no3][add7][add4]": 0.04,
    "ii\u00f865": 0.04,
    "ii64": 0.038,
    "viio43/vi": 0.038,
    "I[no3][add4]": 0.037,
    "#viio64/ii": 0.037,
    "V7[add9]": 0.037,
    "II": 0.037,
    "viio2/ii": 0.037,
    "bII6": 0.037,
    "viio6/IV": 0.035,
    "iii64": 0.033,
    "viio64/V": 0.032,
    "#viio43/iv": 0.03,
    "vi[no5][no3][add6][add4]": 0.03,
    "V/iii": 0.03,
    "viio43/II": 0.03,
    "Fr6": 0.03,
    "V2/vi": 0.03,
    "ii6[no1][add2]": 0.029,
    "iio6": 0.029,
    "I6[no1][add2]": 0.027,
    "V65/iii": 0.027,
    "vii\u00f843": 0.027,
    "I/V": 0.027,
    "#viio65/v": 0.027,
    "I+64": 0.027,
    "It6/ii": 0.026,
    "I[no3][add#2]": 0.024,
    "I[no5][no3][add#4][add#2]": 0.024,
    "I2": 0.024,
    "iio64": 0.024,
    "viio6[no1][add2]": 0.023,
    "ii6[no8][add#7]": 0.023,
    "iv7": 0.023,
    "III6": 0.021,
    "II6": 0.021,
    "IV6[no1][add2]": 0.021,
    "iio6/ii": 0.021,
    "iii7": 0.021,
    "viio/iii": 0.021,
    "ii[no3][add4]": 0.02,
    "viio64/IV": 0.02,
    "IV65": 0.02,
    "viio6/vi": 0.02,
    "bVII": 0.02,
    "V2[no3][add4]": 0.018,
    "bvii64": 0.018,
    "I6[add#11]": 0.018,
    "V+6": 0.018,
    "#viio43/v": 0.018,
    "ii\u00f82/II": 0.018,
    "V7/bIII": 0.018,
    "bIIIM7": 0.018,
    "viio2/iii": 0.018,
    "viio65/iii": 0.018,
    "bII": 0.018,
    "I[add9]": 0.017,
    "V6[no5][add6]": 0.017,
    "V7/iii": 0.017,
    "I[no5][no5][no3][add6][add#4][add#2]": 0.015,
    "IV[no3][add#2]": 0.015,
    "ii43": 0.015,
    "i2": 0.015,
    "ii\u00f82": 0.015,
    "V[add13]": 0.015,
    "bIII": 0.015,
    "ii[no3][add9][add#7][add4]": 0.015,
    "iio/ii": 0.015,
    "viio65/vi": 0.015,
    "#viio6/vi": 0.014,
    "IVM65": 0.014,
    "iii6[no1][add2]": 0.014,
    "V[add9]": 0.014,
    "iv43": 0.014,
    "viio7/IV": 0.014,
    "V64/V": 0.012,
    "V65/bIII": 0.012,
    "IV/IV": 0.012,
    "Cad64/V": 0.012,
    "V[no3][add9][add4]": 0.012,
    "V7[addb9]/vi": 0.012,
    "I[add#11]": 0.012,
    "bII6/vi": 0.012,
    "I/IV": 0.012,
    "V6[no1][add2]": 0.012,
    "bVIM7": 0.012,
    "V2[add4]": 0.012,
    "IV7": 0.012,
    "vii\u00f87/ii": 0.012,
    "v/ii": 0.012,
    "Ger65/IV": 0.012,
    "It6/IV": 0.012,
    "V7[no3][add4]/V": 0.011,
    "IV6/IV": 0.011,
    "IV[no3][add4]": 0.011,
    "vi[no5][add#4]": 0.011,
    "V65/v": 0.011,
    "vi[no5][add6]": 0.011,
    "v64": 0.011,
    "#viio43/vi": 0.009,
    "iv/ii": 0.009,
    "V[no3][add4]/ii": 0.009,
    "ii7[no3][add4]": 0.009,
    "V+65/IV": 0.009,
    "I[no5][add6]": 0.009,
    "#viio7/iii": 0.009,
    "#viio/vi": 0.009,
    "Ger6[no1][add2]": 0.009,
    "IV[add#9]": 0.009,
    "It6/vi": 0.009,
    "V+/IV": 0.009,
    "V[no5][no3][add#7][addb6][add4]": 0.009,
    "ii6[no8][no1][add#7][add2]": 0.009,
    "V[no5][no3][add#4][add#2]": 0.009,
    "V6[no5][no3][add6][add#2]": 0.009,
    "V43/iv": 0.009,
    "viio43/iii": 0.009,
    "viio/vi": 0.009,
    "IV6[no8][add7]": 0.008,
    "IVM7": 0.008,
    "V+7/IV": 0.008,
    "V65/II": 0.008,
    "viio7/II": 0.008,
    "II64": 0.008,
    "iv64/ii": 0.008,
    "V+": 0.008,
    "I6[add14]": 0.007,
    "V7[addb9]": 0.007,
    "IM2": 0.006,
    "#viio43/iii": 0.006,
    "VI6": 0.006,
    "ii[add4]": 0.006,
    "V[no3][add4]/V": 0.006,
    "V65[no3][no1][add4][addb2]": 0.006,
    "#vi\u00f87/ii": 0.006,
    "viio[add#3]/IV": 0.006,
    "V+43/V": 0.006,
    "iii[no3][add4]": 0.006,
    "V[no3][addb9][add4]/ii": 0.006,
    "V[addb9]/ii": 0.006,
    "V6/bVI": 0.006,
    "V/iv": 0.006,
    "#viio7/v": 0.006,
    "viio7/V/ii": 0.006,
    "ii6[no8][no1][add11][add#7][add2]": 0.006,
    "I[no5][no3][add7][add6][add4]": 0.006,
    "vii\u00f87/bIII": 0.006,
    "V6/iii": 0.006,
    "IV64/V": 0.006,
    "I[no3][no3][add4][add#2]": 0.006,
    "#viio43[no1][add2]/ii": 0.006,
    "V[no5][no3][add#7][add6][add4]": 0.006,
    "V7[no3][add4]/vi": 0.006,
    "ii6[no5][add#4]": 0.006,
    "I[add#9][add7]": 0.006,
    "V[no3][add#7][add4]": 0.006,
    "V65[no3][add4]": 0.006,
    "Ger43": 0.006,
    "I[no3][add4][add9]": 0.006,
    "I[add7]": 0.006,
    "ii65[no1][add2]": 0.006,
    "iii6[no8][add#7]": 0.006,
    "#viio6/iv": 0.006,
    "V7/II": 0.006,
    "I6[no3][no1][add4][add2]": 0.006,
    "ii\u00f865/II": 0.006,
    "V6[no5][no3][add#4][add2]": 0.006,
    "#viio2/ii": 0.006,
    "I+6": 0.006,
    "bVII6": 0.006,
    "IV+": 0.006
}