{
    "BWV": "388",
    "CPE": 183,
    "Riemenschneider": 183,
    "Zahn": "4427",
    "analysis_source": "Bach Chorales/riemenschneider183.txt",
    "composer": "Bach, Johann Sebastian",
    "music21": [
        "bwv388.mxl"
    ],
    "remote_score_krn": "https://raw.githubusercontent.com/craigsapp/bach-370-chorales/master/kern/chor183.krn",
    "remote_score_music21": "bach/bwv388.mxl",
    "remote_score_mxl": "https://raw.githubusercontent.com/MarkGotham/Chorale-Corpus/Bach,_Johann_Sebastian/Chorales/183/short_score.mxl",
    "text": "Nun freut euch, lieben Christen gmein",
    "tune": "Nun freut euch, lieben Christen gmein (melody #1)"
}