{
    "BWV": "65.2",
    "CPE": 12,
    "Riemenschneider": 12,
    "Zahn": "192b",
    "analysis_source": "Bach Chorales/riemenschneider012.txt",
    "composer": "Bach, Johann Sebastian",
    "music21": [
        "bwv65.2.mxl"
    ],
    "remote_score_krn": "https://raw.githubusercontent.com/craigsapp/bach-370-chorales/master/kern/chor012.krn",
    "remote_score_music21": "bach/bwv65.2.mxl",
    "remote_score_mxl": "https://raw.githubusercontent.com/MarkGotham/Chorale-Corpus/Bach,_Johann_Sebastian/Chorales/012/short_score.mxl",
    "text": "Ein Kind geborn zu Bethlehem (4)",
    "tune": "Ein Kind geborn zu Bethlehem (Puer natus in Bethlehem)"
}